SoftwaretestingmaterialZh/404.html
SoftwaretestingmaterialZh/CNAME
SoftwaretestingmaterialZh/Dockerfile
SoftwaretestingmaterialZh/LICENSE
SoftwaretestingmaterialZh/LICENSE_ETC
SoftwaretestingmaterialZh/NAV.md
SoftwaretestingmaterialZh/README.md
SoftwaretestingmaterialZh/SUMMARY.md
SoftwaretestingmaterialZh/__init__.py
SoftwaretestingmaterialZh/__main__.py
SoftwaretestingmaterialZh/index.html
SoftwaretestingmaterialZh/update.sh
SoftwaretestingmaterialZh/asset/LXGWWenKaiScreen.ttf
SoftwaretestingmaterialZh/asset/__init__.py
SoftwaretestingmaterialZh/asset/back-to-top.css
SoftwaretestingmaterialZh/asset/back-to-top.js
SoftwaretestingmaterialZh/asset/dark-mode.css
SoftwaretestingmaterialZh/asset/dark-mode.js
SoftwaretestingmaterialZh/asset/docsify-apachecn-footer.js
SoftwaretestingmaterialZh/asset/docsify-baidu-push.js
SoftwaretestingmaterialZh/asset/docsify-baidu-stat.js
SoftwaretestingmaterialZh/asset/docsify-clicker.js
SoftwaretestingmaterialZh/asset/docsify-cnzz.js
SoftwaretestingmaterialZh/asset/docsify-copy-code.min.js
SoftwaretestingmaterialZh/asset/docsify-katex.js
SoftwaretestingmaterialZh/asset/docsify-quick-page.css
SoftwaretestingmaterialZh/asset/docsify-quick-page.js
SoftwaretestingmaterialZh/asset/docsify-sidebar-collapse.min.js
SoftwaretestingmaterialZh/asset/docsify.min.js
SoftwaretestingmaterialZh/asset/edit.css
SoftwaretestingmaterialZh/asset/edit.js
SoftwaretestingmaterialZh/asset/edit.svg
SoftwaretestingmaterialZh/asset/flygon_qr_alipay.png
SoftwaretestingmaterialZh/asset/katex.min.css
SoftwaretestingmaterialZh/asset/left.svg
SoftwaretestingmaterialZh/asset/lxgw-wenkai.css
SoftwaretestingmaterialZh/asset/moon.svg
SoftwaretestingmaterialZh/asset/prism-c.min.js
SoftwaretestingmaterialZh/asset/prism-cpp.min.js
SoftwaretestingmaterialZh/asset/prism-csharp.min.js
SoftwaretestingmaterialZh/asset/prism-darcula.css
SoftwaretestingmaterialZh/asset/prism-java.min.js
SoftwaretestingmaterialZh/asset/prism-javascript.min.js
softwaretestingmaterial_zh-2022.9.14.0.dist-info/METADATA
softwaretestingmaterial_zh-2022.9.14.0.dist-info/WHEEL
softwaretestingmaterial_zh-2022.9.14.0.dist-info/entry_points.txt
softwaretestingmaterial_zh-2022.9.14.0.dist-info/top_level.txt
softwaretestingmaterial_zh-2022.9.14.0.dist-info/RECORD
